jumppng/__init__.py
jumppng/main.py
jumppng-0.2.1.dist-info/METADATA
jumppng-0.2.1.dist-info/WHEEL
jumppng-0.2.1.dist-info/entry_points.txt
jumppng-0.2.1.dist-info/top_level.txt
jumppng-0.2.1.dist-info/RECORD
