Metadata-Version: 2.1
Name: jumppng
Version: 0.2.1
Requires-Dist: Pillow
